README.txt
setup.py
nfogen/__init__.py
nfogen.egg-info/PKG-INFO
nfogen.egg-info/SOURCES.txt
nfogen.egg-info/dependency_links.txt
nfogen.egg-info/entry_points.txt
nfogen.egg-info/requires.txt
nfogen.egg-info/top_level.txt