Metadata-Version: 1.0
Name: nfogen
Version: 0.0.3
Summary: Generate tvshow.nfo files for tv shows
Home-page: template url
Author: Boris Babic
Author-email: boris.ivan.babic@gmail.com
License: UNKNOWN
Platform: UNKNOWN
